comms_lib/__about__.py
comms_lib/__init__.py
comms_lib/cfo.py
comms_lib/dsp.py
comms_lib/pluto.py
comms_lib/pulse.py
comms_lib/qam.py
comms_lib/sequence.py
comms_lib/system.py
comms_lib/system3.py
comms_lib/utils/__init__.py
comms_lib/utils/plot.py
cosmos2025-3.0.1.dist-info/METADATA
cosmos2025-3.0.1.dist-info/WHEEL
cosmos2025-3.0.1.dist-info/RECORD
